mcp_transcriptions_server/__init__.py
mcp_transcriptions_server/openai_transciption.py
mcp_transcriptions_server/server.py
mcp_transcriptions_server-0.1.2.dist-info/METADATA
mcp_transcriptions_server-0.1.2.dist-info/WHEEL
mcp_transcriptions_server-0.1.2.dist-info/entry_points.txt
mcp_transcriptions_server-0.1.2.dist-info/RECORD
