Metadata-Version: 2.4
Name: mcp-transcriptions-server
Version: 0.1.2
Summary: Add your description here
Requires-Python: >=3.13
Requires-Dist: mcp[cli]>=1.16.0
Requires-Dist: openai>=2.1.0
